{
  "App": {
    "Title": "Zer0Talk"
  },
  "Settings": {
    "Title": "设置",
    "Appearance": "外观",
    "General": "常规",
    "Hotkeys": "快捷键",
    "Profile": "个人资料",
    "Network": "网络",
    "Performance": "性能",
    "Accessibility": "辅助功能",
    "About": "关于",
    "DangerZone": "危险区域",
    "LogOut": "登出",
    "Language": "语言",
    "Theme": "主题",
    "Font": "字体",
    "Privacy": "隐私",
    "DefaultPresence": "默认在线状态",
    "Status": "状态",
    "Online": "在线",
    "Away": "离开",
    "DoNotDisturb": "请勿打扰",
    "Offline": "离线",
    "SuppressNotifications": "在请勿打扰模式下禁用通知和音频",
    "NotificationDuration": "通知持续时间",
    "Duration": "持续时间：",
    "Precise": "精确值：",
    "NotificationDurationHelp": "控制通知提示的显示时长。滑块：0.5-20秒，输入框：0.5-30秒。",
    "CurrentSetting": "当前设置：",
    "Seconds": "秒",
    "OfflineAutomatic": "离线状态仅为自动，无法手动选择。",
    "EnableNotificationBellFlash": "启用通知铃声闪烁",
    "NotificationBellFlashHelp": "通知到达时，铃铛图标闪烁10秒",
    "AutoLock": "自动锁定",
    "EnableAutoLock": "启用自动锁定",
    "Minutes": "分钟",
    "LockOnMinimize": "最小化时锁定",
    "LockBlurRadius": "锁定模糊半径",
    "LockBlurHelp": "控制锁定时的模糊强度。0 = 无模糊，10 = 最大模糊。",
    "BlockScreenCapture": "阻止屏幕截图",
    "ScreenCaptureWarning": "仅限Windows；较旧的截图工具可能无法遵守此设置。",
    "KeyVisibility": "密钥可见性",
    "ShowPublicKeys": "在个人资料中显示公钥",
    "Audio": "音频",
    "AudioHelp": "配置不同类型声音的音量级别。主音量作为主控制，各个通道允许微调特定的声音类别。",
    "MainVolume": "主音量",
    "Notifications": "通知",
    "ChatSounds": "聊天声音",
    "SystemTray": "系统托盘",
    "SystemTrayHelp": "控制Zer0Talk如何与Windows系统托盘交互。",
    "ShowSystemTrayIcon": "在系统托盘中显示图标",
    "ShowSystemTrayIconHelp": "在Windows系统托盘中显示Zer0Talk图标以便快速访问",
    "MinimizeToTray": "关闭时最小化到托盘",
    "MinimizeToTrayHelp": "关闭按钮将最小化到系统托盘而不是退出应用程序",
    "RunOnStartup": "Windows启动时运行",
    "RunOnStartupHelp": "Windows启动时自动启动Zer0Talk（最小化到托盘）",
    "Family": "字体族：",
    "Identity": "身份",
    "Username": "用户名",
    "UID": "用户标识",
    "DisplayName": "显示名称",
    "PrevName": "曾用名",
    "PublicKey": "公钥",
    "Avatar": "头像",
    "Choose": "选择...",
    "Clear": "清除",
    "ShareAvatar": "与对等方共享头像",
    "Bio": "个人简介",
    "CustomizeKeyboardShortcuts": "自定义键盘快捷键",
    "HotkeyInstructions": "单击快捷键字段并按下所需的组合键。冲突的分配将被拒绝。",
    "LockApplication": "锁定应用程序",
    "LockApplicationHelp": "快速锁定应用程序以保护您的隐私",
    "Hotkey": "快捷键",
    "PressKeys": "按键...",
    "ResetToDefault": "重置为默认",
    "ClearMessageInput": "清除消息输入",
    "ClearMessageInputHelp": "立即清除消息输入框中的所有文本",
    "HotkeyTips": "💡 提示",
    "HotkeyTipsText": "避免使用系统快捷键，如Alt+F4、Ctrl+C、Win+L等。常见的安全组合使用Ctrl、Ctrl+Shift或Ctrl+Alt配合功能键或字母。",
    "Dark": "深色",
    "Light": "浅色",
    "Sandy": "沙色",
    "Butter": "黄油色",
    "EnterFontFamilyName": "输入字体族名称",
    "OSScalingMessage": "对于UI缩放，请使用您操作系统的显示缩放设置。",
    "AdditionalLanguagesMessage": "更多语言将在未来的更新中添加。",
    "EnterDisplayName": "输入您的显示名称",
    "ApplicationInformation": "应用程序信息",
    "Version": "版本：",
    "Build": "构建：",
    "Developer": "开发者：",
    "Repository": "代码库：",
    "License": "许可证：",
    "Copyright": "版权：",
    "CPU": "处理器",
    "GPU": "显卡",
    "Framerate": "帧率",
    "CCDOffinity": "CCD亲和性：",
    "NotRecommended": "不推荐",
    "EnforceRAMLimit": "强制RAM限制",
    "RAMLimit": "RAM限制：",
    "MBUnlimited": "MB（0 = 无限制）",
    "EnableGPUAcceleration": "启用GPU加速",
    "EnforceVRAMLimit": "强制显存限制",
    "VRAMLimit": "显存限制：",
    "FPSThrottle": "FPS限制：",
    "FPSUnlimited": "帧/秒（0 = 无限制）",
    "RefreshRateThrottle": "刷新率限制：",
    "HzUnlimited": "赫兹（0 = 无限制）",
    "BackgroundFramerate": "后台帧率：",
    "FPS": "帧/秒",
    "AccessibilitySettings": "辅助功能设置",
    "AccessibilityOSMessage": "大多数辅助功能由您的操作系统控制：",
    "AccessibilityTitle": "辅助功能",
    "DisplayScaling": "• 显示缩放：",
    "DisplayScalingPath": "Windows显示设置 > 缩放和布局",
    "HighContrast": "• 高对比度：",
    "HighContrastPath": "Windows设置 > 辅助功能 > 对比度主题",
    "Animations": "• 动画：",
    "AnimationsPath": "Windows设置 > 辅助功能 > 视觉效果",
    "CursorSize": "• 光标大小：",
    "CursorSizePath": "Windows设置 > 辅助功能 > 鼠标指针和触摸",
    "TextCursor": "• 文本光标：",
    "TextCursorPath": "Windows设置 > 辅助功能 > 文本光标",
    "Tab": "• Tab",
    "TabDescription": "– 在控件间向前移动",
    "ShiftTab": "• Shift+Tab",
    "ShiftTabDescription": "– 在控件间向后移动",
    "SpaceEnter": "• 空格/回车",
    "SpaceEnterDescription": "– 激活按钮和开关",
    "ArrowKeys": "• 方向键",
    "ArrowKeysDescription": "– 在列表、菜单和下拉菜单中导航",
    "Esc": "• Esc",
    "EscDescription": "– 关闭对话框和覆盖层",
    "CtrlL": "• Ctrl+L",
    "CtrlLDescription": "– 锁定应用程序（可在快捷键中自定义）",
    "KeyboardNavigation": "键盘导航",
    "ShowKeyboardFocusIndicators": "显示键盘焦点指示器",
    "EnhancedKeyboardNavigation": "增强键盘导航",
    "NavigationKeys": "导航键：",
    "NavigationHelp": "所有窗口和面板都支持完整的键盘导航。焦点指示器将突出显示活动控件。",
    "FontRendering": "字体渲染",
    "OSFontSmoothing": "操作系统字体平滑：",
    "FontSmoothingMessage": "字体平滑由您的操作系统控制。请在操作系统显示设置中更改。",
    "DebugTools": "调试工具",
    "Logging": "日志记录",
    "EnableLogging": "启用日志记录",
    "PerformanceWarning": "性能警告",
    "PerformanceWarningText": "日志记录会导致显著的性能下降。仅在主动跟踪问题或调试时启用。故障排除完成后立即禁用。",
    "LogMaintenance": "日志维护",
    "AutoTrimUILog": "自动修剪UI日志",
    "MaxEntries": "保留的最大条目数",
    "RetentionDays": "保留窗口（天）",
    "SizeCap": "大小上限",
    "LastMaintenance": "上次维护",
    "RunMaintenanceNow": "立即运行维护",
    "PurgeAllLogs": "清除所有日志",
    "PurgeAllLogsTooltip": "删除logs目录中的所有日志文件（临时调试数据）",
    "ConnectionSettings": "连接设置",
    "RelaySettings": "中继设置",
    "Port": "端口",
    "PortLabel": "端口：",
    "PortDescription": "Zer0Talk用于P2P连接的端口号。默认为26264。更改此设置需要重启应用程序。",
    "DedicatedPeerNode": "专用对等节点",
    "EnableDedicatedPeerNode": "启用为专用对等节点（需要端口转发）",
    "DedicatedPeerNodeInfo": "专用对等节点：",
    "EnablesUPnP": "• 启用UPnP端口映射以实现WAN可达性（需要路由器支持）",
    "MakesNodeAccessible": "• 使您的节点可从本地网络外部访问",
    "ImprovesConnectivity": "• 改善所有对等方的直接P2P连接",
    "DoesNotRelay": "• 不中继加密的消息流量 - 仅帮助NAT穿透",
    "RequiresPortForwarding": "• 如果UPnP失败，需要手动端口转发（将端口26264 TCP转发到此机器）",
    "RelayDescription1": "当直接P2P和NAT穿透失败时，中继服务器提供最后的连接手段。",
    "RelayDescription2": "所有消息保持端到端加密 - 中继仅转发加密流量。",
    "RelayFallback": "中继回退",
    "EnableRelayFallback": "为被阻止的连接启用中继回退",
    "RelayServer": "中继服务器",
    "Requirements": "要求：",
    "RequiresDedicatedRelay": "• 需要具有公共IP或DNS名称的专用中继服务器",
    "ServerMustBeConfigured": "• 服务器必须配置为接受Zer0Talk中继协议连接",
    "RelayFormat": "• 格式：主机名:端口 或 IP:端口（例如，relay.example.com:443）",
    "LeaveBlankToDisable": "• 留空以禁用中继回退并仅依赖直连/NAT穿透",
    "KnownDedicatedPeerNodes": "已知的专用对等节点",
    "Add": "添加",
    "Remove": "移除",
    "DiscoveredPeers": "已发现的对等方",
    "LocationsEstimated": "（位置是估计的，并不完全准确）",
    "BlockSelected": "阻止所选",
    "UnblockSelected": "取消阻止所选",
    "Node": "节点",
    "Block": "阻止",
    "Auto": "自动",
    "CCD0": "CCD 0",
    "CCD1": "CCD 1",
    "BothCCDs": "两个CCD",
    "AboutName": "名称：",
    "AboutPlatform": "平台：",
    "AboutAuthor": "作者：",
    "AboutFrameworkInfo": "框架信息",
    "AboutAvaloniaUI": "Avalonia UI：",
    "AboutDotNetRuntime": ".NET运行时：",
    "AboutLinksResources": "链接与资源",
    "AboutDocumentation": "文档",
    "AboutPrivacyPolicy": "隐私政策",
    "AboutAcknowledgments": "致谢",
    "AboutBuiltWithAvalonia": "使用 Avalonia UI 构建 - 适用于 .NET 的跨平台 XAML UI 框架",
    "AboutSpecialThanks": "特别感谢开源社区的贡献和支持。",
    "MessageBurnSecurity": "消息销毁安全",
    "MessageBurnSecurityDesc": "选择销毁对话的安全级别。标准更快，增强提供最大安全性。",
    "MessageBurnStandard": "标准（3遍）",
    "MessageBurnStandardDesc": "用随机位、lorem文本、交替模式和零覆盖数据。",
    "MessageBurnStandardTooltip": "平衡的安全性和良好的性能",
    "MessageBurnEnhanced": "增强（6遍）",
    "MessageBurnEnhancedDesc": "用随机数据、0xFF、0x00、随机、0xAA和0x55模式覆盖，以获得最大安全性。",
    "MessageBurnEnhancedTooltip": "最大安全性，较慢但更彻底",
    "DangerZoneTitle": "⚠️ 危险区",
    "DangerZoneWarning": "这些操作是不可逆的，将永久删除您的数据。",
    "DeleteAccount": "删除账户",
    "WhatHappens": "删除账户时会发生什么：",
    "MessagesDeleted": "• 您的所有消息将被永久删除",
    "ContactListRemoved": "• 您的联系人列表将被移除",
    "ProfileErased": "• 您的个人资料信息将被清除",
    "RemovedFromConversations": "• 您将从所有对话中被移除",
    "CannotUndo": "• 此操作无法撤销",
    "DeleteAccountWarning": "一旦删除您的账户，将无法恢复。这将永久删除您的账户并清除此设备上的所有本地数据。",
    "TypeConfirmationCode": "请输入以下代码以确认：",
    "EnterConfirmationCode": "输入确认代码...",
    "DeleteAccountButton": "删除账户",
    "PurgeAllMessages": "清除所有消息",
    "WhatHappensPurge": "清除所有消息时会发生什么：",
    "ConversationsDeleted": "• 每个对话将被永久删除",
    "OutboxRemoved": "• 所有待发送的消息将被移除",
    "ArchivesOverwritten": "• 加密档案将被安全覆盖",
    "RecoveryImpossible": "• 将无法恢复",
    "PurgeWarning": "安全地从此设备删除每个对话和待发送的消息。此过程在删除前覆盖加密档案，使恢复变得不可能。",
    "PurgeUseCase": "如果您要停用设备或需要清空数据，请使用此功能。",
    "TypePurgeConfirm": "输入'PURGE-ALL-DATA'以确认：",
    "TypePurgeAllData": "输入：PURGE-ALL-DATA",
    "PurgeAllMessagesButton": "清除所有消息",
    "ExportData": "导出数据",
    "ExportDataDescription": "在删除账户之前下载您的数据副本。这包括您的消息、联系人和设置。",
    "ExportDataButton": "导出数据",
    "SignOut": "登出",
    "SignOutDescription": "登出将断开您与应用程序的连接，并需要您再次输入密码短语才能访问您的账户。",
    "DataRemains": "您的数据将保持安全存储在本地，并在您重新登录时可用。",
    "CurrentSession": "当前会话",
    "SessionStatus": "状态：",
    "Active": "活动",
    "LastActivity": "最后活动：",
    "JustNow": "刚刚",
    "ReadyToSignOut": "准备好登出了吗？",
    "SignOutPrompt": "点击下面的按钮登出您的账户。您需要密码短语才能重新登录。",
    "SignOutButton": "登出",
    "SecurityReminder": "🔒 安全提醒",
    "SecurityReminderText": "使用共享或公共计算机时，请务必登出以保护您的隐私和安全。",
    "LanguageHelp": "Change the application language",
    "ThemeHelp": "Select the overall application theme",
    "FontHelp": "Override the UI font family (leave blank for default)",
    "DefaultPresenceHelp": "Sets your default status when the app is running",
    "AutoLockHelp": "Automatically lock the app after inactivity",
    "AutoLockMinutesHelp": "Number of idle minutes before locking",
    "LockOnMinimizeHelp": "Lock immediately when the window is minimized",
    "ShowPublicKeysHelp": "Display public keys in profile views",
    "BioHelp": "Add a short profile bio shown to your contacts",
    "StartMinimized": "Start minimized to tray",
    "StartMinimizedHelp": "Launch Zer0Talk in the system tray instead of showing the main window",
    "EnforceRAMLimitHelp": "Limit memory usage for the app",
    "RamLimitHelp": "Maximum RAM usage in MB (0 = unlimited)",
    "EnableGpuAccelerationHelp": "Use hardware acceleration for rendering when available",
    "EnforceVramLimitHelp": "Limit GPU memory usage for the app",
    "VramLimitHelp": "Maximum VRAM usage in MB (0 = unlimited)",
    "FpsThrottleHelp": "Limit UI rendering frames per second (0 = unlimited)",
    "RefreshRateThrottleHelp": "Limit display refresh rate used by the app (0 = unlimited)",
    "BackgroundFramerateHelp": "Limit UI framerate when the app is unfocused",
    "ShowKeyboardFocusHelp": "Highlight the currently focused control",
    "EnhancedKeyboardNavigationHelp": "Enable additional keyboard navigation behaviors",
    "AutoTrimUILogHelp": "Automatically trim the UI log to the limits below",
    "DebugUiLogMaxLinesHelp": "Maximum number of UI log entries to keep",
    "DebugLogRetentionDaysHelp": "How many days to retain debug logs",
    "DebugLogSizeHelp": "Maximum total size of debug logs before trimming",
    "DedicatedPeerNodeHelp": "Make this device act as a dedicated peer node",
    "RelayFallbackHelp": "Use a relay server when direct P2P connections fail",
    "RelayServerHelp": "Relay hostname and port (leave blank to disable)",
    "KnownDedicatedPeerNodesHelp": "Add a host:port peer node to prefer for discovery",
    "AddBadActorIpHelp": "Add a single IP address to block",
    "AddIpRangeHelp": "Add a CIDR IP range to block"
  },
  "Notifications": {
    "NewMessage": "新消息",
    "Error": "错误",
    "Warning": "警告",
    "Information": "信息",
    "Success": "成功",
    "GoToChat": "转到聊天",
    "MessageFrom": "来自的消息",
    "SentYouAMessage": "给您发送了一条消息",
    "UnknownAccount": "未知",
    "SecurityEventDetected": "检测到安全事件。",
    "KeyMismatchBlocked": "检测到密钥不匹配。会话已被阻止。"
  },
  "Common": {
    "Save": "保存",
    "Cancel": "取消",
    "OK": "确定",
    "Yes": "是",
    "No": "否",
    "Apply": "应用",
    "Close": "关闭"
  },
  "Dialogs": {
    "ConfirmLogout": "您确定要登出吗？",
    "ConfirmDelete": "您确定要删除此项吗？",
    "ConfirmClear": "您确定要清除此项吗？",
    "UnsavedChanges": "您有未保存的更改。是否要保存？",
    "Success": "成功",
    "Failed": "失败",
    "Confirm": "确认",
    "AreYouSure": "您确定吗？",
    "BurnConversationTitle": "销毁对话",
    "BurnConversationMessage": "销毁与{0}的对话？\n\n此过程使用您配置的安全级别执行不可逆的销毁（设置 → 危险区 → 消息销毁安全）：\n• 用多次安全覆盖存储的消息\n• 应用加密随机和固定位模式\n• 删除残留的消息和发件箱文件\n\n完成后，对话将无法恢复。",
    "BurnNow": "立即销毁",
    "ClearInvitesTitle": "拒绝所有邀请",
    "ClearInvitesMessage": "您确定要拒绝所有待处理的联系人邀请吗？此操作无法撤销。",
    "RejectAll": "全部拒绝"
  },
  "MainWindow": {
    "ToggleContacts": "切换联系人",
    "OpenNotifications": "打开通知",
    "LockLogout": "登出",
    "Minimize": "最小化",
    "Maximize": "最大化/还原",
    "Close": "关闭",
    "Home": "主页",
    "Monitoring": "监控",
    "Logs": "日志",
    "Settings": "设置",
    "Contacts": "联系人",
    "AddContact": "添加联系人",
    "ViewProfile": "查看个人资料",
    "CopyUID": "复制UID",
    "SetSimulatedPresence": "设置模拟在线状态",
    "RemoveContact": "移除联系人",
    "Simulated": "模拟",
    "Trusted": "受信任",
    "Encrypted": "已加密",
    "BurnConversation": "永久销毁对话",
    "ChatEncrypted": "聊天已端到端加密",
    "SimulatedContact": "模拟联系人（回环）",
    "Bold": "粗体（**文本**）",
    "Italic": "斜体（*文本*）",
    "Underline": "下划线（__文本__）",
    "StrikeThrough": "删除线（~~文本~~）",
    "Quote": "引用（> 文本）",
    "Code": "代码（`文本` 或 ```块```）",
    "Spoiler": "剧透（||文本||）",
    "TypeMessage": "输入消息",
    "SendMessage": "发送消息",
    "JumpToPresent": "跳转到当前",
    "JumpToLatest": "跳转到最新消息",
    "PendingInvites": "待处理的邀请",
    "Previous": "上一个",
    "Next": "下一个",
    "ClearInvites": "清除邀请",
    "MarkAllRead": "标记所有消息为已读",
    "ClearAllAlerts": "清除所有提醒",
    "Messages": "消息",
    "Alerts": "提醒",
    "Accept": "接受",
    "Reject": "拒绝",
    "NoPendingInvites": "没有待处理的邀请。",
    "NoRecentMessages": "没有最近的消息。",
    "NoAlerts": "没有提醒。",
    "Incoming": "传入",
    "Outgoing": "传出",
    "Unread": "未读",
    "Read": "已读",
    "MessageFallback": "消息",
    "AlertFallback": "提醒",
    "SecurityEvent": "安全事件",
    "OpenChat": "打开聊天",
    "UidPrefix": "用户ID:",
    "PrevName": "曾用名",
    "Changes": "更改",
    "About": "关于",
    "Verify": "验证",
    "SaveSimulated": "保存（模拟）",
    "OfflineMessage": "您处于离线状态。消息将在您重新连接时发送。",
    "MessagePending": "消息待发送 - 联系人离线",
    "Sending": "正在发送消息...",
    "MessageSent": "消息已发送",
    "MessageRead": "联系人已读消息",
    "MessageReceived": "消息已接收",
    "Edited": "（已编辑）",
    "Edit": "编辑",
    "Delete": "删除",
    "ThemeEditor": "主题编辑器",
    "Identity": "身份",
    "Presence": "状态",
    "CopyPublicKey": "复制公钥",
    "CloseEsc": "关闭 (Esc)",
    "Invisible": "隐身",
    "StatusBar.ConnectedPeers": "已连接的对等方",
    "StatusBar.StreamerMode": "直播模式",
    "StatusBar.StreamerModeActive": "直播模式",
    "ViewVerificationHistory": "查看历史",
    "SearchContacts": "搜索联系人...",
    "ConnectionDirect": "直接连接",
    "ConnectionRelay": "中继连接",
    "DeliveryPending": "发送中...",
    "DeliverySent": "已发送",
    "DeliveryDelivered": "已送达",
    "ChatEncryptedTransport": "传输已加密（身份未必已验证）",
    "VerifiedBadgeTooltip": "已通过信任仪式验证身份",
    "Fingerprint": "指纹",
    "VerifiedOn": "验证于",
    "VerificationHistory": "验证历史",
    "NoVerificationHistory": "暂无验证记录。",
    "NeverVerified": "从未",
    "Reverify": "重新验证",
    "IdentityVsEncryptionHint": "盾牌验证身份；锁表示加密传输。",
    "VersionMismatchTooltip": "版本不匹配 \u2014 对方使用 v{0}（你：v{1}）"
  },
  "ThemeEditor": {
    "Title": "Zer0Talk 主题编辑器",
    "Undo": "撤销",
    "Redo": "重做",
    "History": "历史记录",
    "NewTheme": "新建主题",
    "OpenTheme": "打开主题",
    "SaveTheme": "保存主题",
    "SaveThemeAs": "主题另存为",
    "SearchThemes": "搜索主题",
    "ThemeMetadata": "主题元数据",
    "NameLabel": "名称：",
    "AuthorLabel": "作者：",
    "VersionLabel": "版本：",
    "DescriptionLabel": "描述：",
    "EditMetadata": "编辑元数据",
    "SystemAccentOverrides": "系统强调色覆盖",
    "SystemAccentDescription1": "覆盖系统提供的强调色，防止系统颜色透出（例如蓝色高亮）。",
    "SystemAccentDescription2": "留空可使用系统颜色。设置全部 4 项可实现完整控制。点击颜色预览可打开取色器。",
    "PrimaryAccent": "主强调色：",
    "SecondaryAccent": "次强调色：",
    "TertiaryAccent": "第三强调色：",
    "QuaternaryAccent": "第四强调色：",
    "HoverAccent": "悬停强调色：",
    "SubtleHover": "轻微悬停：",
    "MediumHover": "中等悬停：",
    "ClickToOpenColorPicker": "点击以打开取色器",
    "ClearToUseOsColor": "清空以使用系统颜色",
    "SystemAltOverrides": "系统替代色覆盖（分层与深度）",
    "SystemAltDescription1": "覆盖系统提供的替代层颜色，用于分层、深度效果和半透明叠加层。",
    "SystemAltDescription2": "用于控制次级背景和分层 UI 元素。在深色主题中通常为半透明白色。",
    "AltHigh": "Alt 高:",
    "AltMediumHigh": "Alt 中高:",
    "AltMedium": "Alt 中:",
    "AltMediumLow": "Alt 中低:",
    "AltLow": "Alt 低:",
    "SystemBaseOverrides": "系统基础色覆盖（基础层）",
    "SystemBaseDescription": "这些颜色控制背景层、表面以及核心 UI 基础元素。",
    "BaseHigh": "Base 高:",
    "BaseMediumHigh": "Base 中高:",
    "BaseMedium": "Base 中:",
    "BaseMediumLow": "Base 中低:",
    "BaseLow": "Base 低:",
    "BaseHighHelp": "高对比度背景和表面",
    "BaseMediumHighHelp": "中高对比度表面",
    "BaseMediumHelp": "中等对比度背景",
    "BaseMediumLowHelp": "中低对比度表面",
    "BaseLowHelp": "低对比度背景",
    "SystemChromeOverrides": "系统 Chrome 颜色覆盖（窗口与边框）",
    "SystemChromeDescription": "这些颜色控制窗口 chrome、框架、边框、标题栏和结构性 UI 元素。",
    "ChromeAltLow": "Chrome Alt 低:",
    "ChromeBlackHigh": "Chrome 黑色 高:",
    "ChromeBlackLow": "Chrome 黑色 低:",
    "ChromeBlackMedium": "Chrome 黑色 中:",
    "ChromeBlackMediumLow": "Chrome 黑色 中低:",
    "ChromeDisabledHigh": "Chrome 禁用 高:",
    "ChromeDisabledLow": "Chrome 禁用 低:",
    "ChromeGray": "Chrome 灰色:",
    "ChromeHigh": "Chrome 高:",
    "ChromeLow": "Chrome 低:",
    "ChromeMedium": "Chrome 中:",
    "ChromeMediumLow": "Chrome 中低:",
    "ChromeWhite": "Chrome 白色:",
    "ChromeAltLowHelp": "替代的低对比度 chrome",
    "ChromeBlackHighHelp": "纯黑色 chrome 元素",
    "ChromeBlackLowHelp": "非常深色的 chrome 元素",
    "ChromeBlackMediumHelp": "中等深色的 chrome 元素",
    "ChromeBlackMediumLowHelp": "中低深色 chrome",
    "ChromeDisabledHighHelp": "禁用的 UI 元素，高对比度",
    "ChromeDisabledLowHelp": "禁用的 UI 元素，低对比度",
    "ChromeGrayHelp": "中性灰色 chrome 元素",
    "ChromeHighHelp": "高对比度 chrome",
    "ChromeLowHelp": "低对比度 chrome",
    "ChromeMediumHelp": "中等对比度 chrome",
    "ChromeMediumLowHelp": "中低对比度 chrome",
    "ChromeWhiteHelp": "纯白色 chrome 元素",
    "ColorOverrides": "颜色覆盖",
    "ColorsLabel": "颜色",
    "ColorOverridesDescription": "为主题定义自定义颜色。点击颜色预览可打开取色器。",
    "ResetToDefault": "恢复默认",
    "Gradients": "渐变",
    "GradientsLabel": "渐变",
    "EditGradient": "编辑渐变",
    "SaveGradient": "保存渐变",
    "CancelEdit": "取消编辑",
    "StartColorLabel": "起始颜色：",
    "EndColorLabel": "结束颜色：",
    "AngleLabel": "角度 (0-360°)：",
    "ClearGradient": "清除渐变",
    "ClearGradientHelp": "将两种颜色都设为背景色（移除渐变效果）",
    "ApplyPresetLabel": "应用预设：",
    "ThemeInfo": "主题信息",
    "EditStatus": "编辑状态",
    "RecentColors": "最近颜色",
    "ReadyStatus": "已准备好编辑主题",
    "CanUndoLabel": "可撤销",
    "CanRedoLabel": "可重做",
    "EditingColorLabel": "正在编辑的颜色",
    "EditingGradientLabel": "正在编辑的渐变",
    "BatchModeLabel": "批处理模式"
  },
  "AccountCreation": {
    "Title": "创建账户",
    "CreateLocalAccount": "创建您的本地账户",
    "OnTop": "置顶",
    "KeepOnTop": "将此窗口保持在其他窗口之上",
    "PickUsername": "选择用户名（6-24个字符）。我们将生成安全的密钥对和UID。",
    "DisplayName": "显示名称",
    "Username": "用户名",
    "Cancel": "取消",
    "Create": "创建"
  },
  "Unlock": {
    "Title": "Zer0Talk 登录",
    "EnterPassphrase": "输入密码短语以解锁",
    "Passphrase": "密码短语",
    "RememberPassphrase": "记住密码短语",
    "RememberTooltip": "安全地存储您的密码短语。请勿在共享设备上启用此功能。",
    "CloseApp": "关闭应用程序",
    "LostPassphrase": "忘记密码短语？",
    "SignIn": "登录",
    "NewPassphraseWarning": "请立即记下这个新密码短语。以后您将无法恢复它。",
    "ISavedIt": "我已保存"
  },
  "AddContact": {
    "Title": "添加联系人",
    "EnterUID": "输入联系人的UID（无前缀）。发现是自动的。",
    "UID": "UID",
    "UIDPlaceholder": "例如，7XKQ9Z8P",
    "ExpectedPublicKey": "预期的公钥（十六进制，可选）",
    "PublicKeyPlaceholder": "abcdef...",
    "SimulatedContact": "模拟联系人",
    "Cancel": "取消",
    "SendRequest": "发送请求"
  },
  "Monitoring": {
    "Title": "监控",
    "NAT": "NAT：",
    "Retry": "重试",
    "RetryTooltip": "重新运行映射验证和回环测试",
    "StatusLegend": "状态图例",
    "Searching": "搜索中",
    "Failure": "失败",
    "Success": "成功",
    "TrafficBytesPerSec": "流量（字节/秒）",
    "Refresh": "刷新",
    "Ports": "端口：",
    "Gateway": "网关：",
    "ExternalIP": "外部IP：",
    "Service": "服务：",
    "AltServices": "备用服务：",
    "MapPing": "映射/Ping：",
    "MapAt": "映射 @",
    "VerifyAt": "· 验证 @",
    "Punch": "打孔：",
    "Hairpin": "| 回环：",
    "Discovery": "发现：",
    "Attempts": "尝试次数：",
    "Backoff": "退避：",
    "RestartDiscovery": "重启发现",
    "LastAttempt": "最后尝试：",
    "LastSuccess": "· 最后成功：",
    "DiagnosticsLog": "诊断日志",
    "ShowLog": "显示日志",
    "TextSizeForLog": "日志文本大小",
    "Close": "关闭"
  },
  "LogViewer": {
    "Title": "日志查看器",
    "Minimize": "最小化",
    "Close": "关闭",
    "LogsDirectory": "日志目录",
    "Refresh": "刷新",
    "RefreshTooltip": "重新扫描日志目录",
    "ReloadFile": "重新加载文件",
    "ReloadTooltip": "重新加载当前选定的日志",
    "TrimThisLog": "修剪此日志",
    "TrimTooltip": "应用调试维护设置以修剪此日志文件",
    "CopyPath": "复制路径",
    "CopyPathTooltip": "复制所选日志的完整路径",
    "OpenFolder": "打开文件夹",
    "OpenFolderTooltip": "在文件资源管理器中打开日志文件夹",
    "Autoscroll": "自动滚动",
    "AutoscrollTooltip": "保持视图固定在最新的日志条目",
    "JumpToBottom": "Jump to bottom",
    "Loading": "加载中...",
    "NoLogFiles": "未找到日志文件",
    "RefreshToScan": "使用刷新重新扫描日志目录。"
  },
  "LostPassphrase": {
    "Title": "忘记密码短语恢复",
    "Warning": "这将生成一个新的密码短语并重新加密您的数据。继续吗？",
    "Username": "用户名",
    "Cancel": "取消",
    "GenerateNew": "生成新密码短语",
    "WriteDownWarning": "请立即记下这个新密码短语。以后您将无法恢复它。",
    "ISavedIt": "我已保存"
  },
  "Loading": {
    "Title": "Zer0Talk - 加载中",
    "Initializing": "正在初始化安全消息系统..."
  }
}
